{"48000":{"estado":"Jalisco","ciudades":["Unión de Tula"],"colonias":["Centro Unión de Tula","San Juan","Trigomil"]},"48002":{"estado":"Jalisco","ciudades":["Unión de Tula"],"colonias":["Puente la Trinidad","Santa Ana"]},"48010":{"estado":"Jalisco","ciudades":["Unión de Tula"],"colonias":["El Bonete","Santa Rosa de Lima"]},"48017":{"estado":"Jalisco","ciudades":["Unión de Tula"],"colonias":["La Taberna"]},"48020":{"estado":"Jalisco","ciudades":["Unión de Tula"],"colonias":["San Clemente"]},"48026":{"estado":"Jalisco","ciudades":["Unión de Tula"],"colonias":["La Piñuela","Santa Fe","Tacotán (La Alpatahua)"]},"48030":{"estado":"Jalisco","ciudades":["Unión de Tula"],"colonias":["San Gaspar"]},"48035":{"estado":"Jalisco","ciudades":["Unión de Tula"],"colonias":["Ixtlahuacán de Santiago","La Alcaparrosa"]},"48040":{"estado":"Jalisco","ciudades":["Unión de Tula"],"colonias":["San Agustin"]},"48047":{"estado":"Jalisco","ciudades":["Unión de Tula"],"colonias":["San Cayetano"]},"48048":{"estado":"Jalisco","ciudades":["Unión de Tula"],"colonias":["San José de Ávila"]},"48050":{"estado":"Jalisco","ciudades":["Ayutla"],"colonias":["Ayutla","Capilla de Rayo","Tepantla","Tepetates"]},"48052":{"estado":"Jalisco","ciudades":["Ayutla"],"colonias":["El Zapote de Chávez","San Francisco Del Rincón"]},"48060":{"estado":"Jalisco","ciudades":["Ayutla"],"colonias":["Santo Domingo"]},"48064":{"estado":"Jalisco","ciudades":["Ayutla"],"colonias":["Casa Blanca","El Vado"]},"48065":{"estado":"Jalisco","ciudades":["Ayutla"],"colonias":["El Tambor"]},"48070":{"estado":"Jalisco","ciudades":["Ayutla"],"colonias":["San Pedro"]},"48075":{"estado":"Jalisco","ciudades":["Ayutla"],"colonias":["El Colomo"]},"48076":{"estado":"Jalisco","ciudades":["Ayutla"],"colonias":["El Arrayán","El Salto (Cerritos)"]},"48077":{"estado":"Jalisco","ciudades":["Ayutla"],"colonias":["Tepospizaloya"]},"48078":{"estado":"Jalisco","ciudades":["Ayutla"],"colonias":["San Pío"]},"48080":{"estado":"Jalisco","ciudades":["Ayutla"],"colonias":["Santa Rosalía"]},"48084":{"estado":"Jalisco","ciudades":["Ayutla"],"colonias":["El Rosario","La Cañada del Carmen"]},"48086":{"estado":"Jalisco","ciudades":["Ayutla"],"colonias":["Las Peruleras"]},"48087":{"estado":"Jalisco","ciudades":["Ayutla"],"colonias":["San Antonio de los Moran"]},"48089":{"estado":"Jalisco","ciudades":["Ayutla"],"colonias":["San Miguel de La Sierra"]},"48090":{"estado":"Jalisco","ciudades":["Ayutla"],"colonias":["Yerbabuena de las Palmas"]},"48092":{"estado":"Jalisco","ciudades":["Ayutla"],"colonias":["Santa Mónica (Ruiz Cortinez)"]},"48093":{"estado":"Jalisco","ciudades":["Ayutla"],"colonias":["San Juan Cacoma"]},"48095":{"estado":"Jalisco","ciudades":["Ayutla"],"colonias":["El Zapotillo","Paredones"]},"48096":{"estado":"Jalisco","ciudades":["Ayutla"],"colonias":["Buckingham","El Salto de Latillas","Los Sauces"]},"48098":{"estado":"Jalisco","ciudades":["Ayutla"],"colonias":["La Joya"]},"48100":{"estado":"Jalisco","ciudades":["Atenguillo"],"colonias":["Atenguillo"]},"48110":{"estado":"Jalisco","ciudades":["Atenguillo"],"colonias":["San Pablo"]},"48120":{"estado":"Jalisco","ciudades":["Atenguillo"],"colonias":["El Ranchito (Espíritu Santo)"]},"48130":{"estado":"Jalisco","ciudades":["Atenguillo"],"colonias":["Los Volcanes"]},"48135":{"estado":"Jalisco","ciudades":["Atenguillo"],"colonias":["San José de los Andrade"]},"48136":{"estado":"Jalisco","ciudades":["Atenguillo"],"colonias":["Santa Bárbara"]},"48139":{"estado":"Jalisco","ciudades":["Atenguillo"],"colonias":["Ahuacatepec"]},"48140":{"estado":"Jalisco","ciudades":["Atenguillo"],"colonias":["San Antonio de los Macedo"]},"48145":{"estado":"Jalisco","ciudades":["Atenguillo"],"colonias":["Las Cebollas"]},"48146":{"estado":"Jalisco","ciudades":["Atenguillo"],"colonias":["El Rodeo"]},"48150":{"estado":"Jalisco","ciudades":["Cuautla"],"colonias":["Cuautla"]},"48152":{"estado":"Jalisco","ciudades":["Cuautla"],"colonias":["Cañada Grande"]},"48153":{"estado":"Jalisco","ciudades":["Cuautla"],"colonias":["Tierras Blancas"]},"48154":{"estado":"Jalisco","ciudades":["Cuautla"],"colonias":["Suelos Duros"]},"48155":{"estado":"Jalisco","ciudades":["Cuautla"],"colonias":["Chilacayote"]},"48159":{"estado":"Jalisco","ciudades":["Cuautla"],"colonias":["Tototlán del Oro"]},"48160":{"estado":"Jalisco","ciudades":["Atengo"],"colonias":["Trigo de Alteñas"]},"48165":{"estado":"Jalisco","ciudades":["Atengo"],"colonias":["Tacota"]},"48166":{"estado":"Jalisco","ciudades":["Atengo"],"colonias":["El Macuchi (La Trinidad)"]},"48170":{"estado":"Jalisco","ciudades":["Atengo"],"colonias":["San Pedro la Chale"]},"48175":{"estado":"Jalisco","ciudades":["Atengo"],"colonias":["Yerbabuena"]},"48180":{"estado":"Jalisco","ciudades":["Atengo"],"colonias":["Soyatlan Del Oro"]},"48185":{"estado":"Jalisco","ciudades":["Atengo"],"colonias":["Agostadero","El Ojo de Agua","El Salitre"]},"48190":{"estado":"Jalisco","ciudades":["Atengo"],"colonias":["Atengo"]},"48193":{"estado":"Jalisco","ciudades":["Atengo"],"colonias":["Cofradía de Lepe"]},"48199":{"estado":"Jalisco","ciudades":["Atengo"],"colonias":["Huaxtla"]},"48200":{"estado":"Jalisco","ciudades":["Talpa de Allende"],"colonias":["El Cerrito","Jardines de Talpa","La Ciénega","La Mesa","La Parota","Lomas de San Francisco","Naranjo","Playas de Pozonextle","Pozos Sarcos","San Francisco","San Miguel","Talpa de Allende Centro","Villas Del Rosario"]},"48210":{"estado":"Jalisco","ciudades":["Talpa de Allende"],"colonias":["La Cañada"]},"48211":{"estado":"Jalisco","ciudades":["Talpa de Allende"],"colonias":["Cabos"]},"48212":{"estado":"Jalisco","ciudades":["Talpa de Allende"],"colonias":["Los Ocotes","Los Zapotes"]},"48213":{"estado":"Jalisco","ciudades":["Talpa de Allende"],"colonias":["El Rincón de Cabos (El Rincón)"]},"48220":{"estado":"Jalisco","ciudades":["Talpa de Allende"],"colonias":["Cuale"]},"48240":{"estado":"Jalisco","ciudades":["Talpa de Allende"],"colonias":["Concepción del Bramador (La Concha)"]},"48245":{"estado":"Jalisco","ciudades":["Talpa de Allende"],"colonias":["Desmoronado (El Real)"]},"48247":{"estado":"Jalisco","ciudades":["Talpa de Allende"],"colonias":["Los Encinos"]},"48250":{"estado":"Jalisco","ciudades":["Talpa de Allende"],"colonias":["La Cuesta"]},"48255":{"estado":"Jalisco","ciudades":["Talpa de Allende"],"colonias":["La Esperanza","Santa Julia (Rajas Paradas)"]},"48256":{"estado":"Jalisco","ciudades":["Talpa de Allende"],"colonias":["Santa Lucía de la Cuesta","Soyatan"]},"48259":{"estado":"Jalisco","ciudades":["Talpa de Allende"],"colonias":["Las Colonias"]},"48260":{"estado":"Jalisco","ciudades":["Puerto Vallarta"],"colonias":["Las Palmas de Arriba"]},"48262":{"estado":"Jalisco","ciudades":["Puerto Vallarta"],"colonias":["Tebelchia (El Roble)"]},"48264":{"estado":"Jalisco","ciudades":["Puerto Vallarta"],"colonias":["La Mesa del Veladero"]},"48265":{"estado":"Jalisco","ciudades":["Puerto Vallarta"],"colonias":["El Colorado","El Zancudo","Verde Valle"]},"48266":{"estado":"Jalisco","ciudades":["Puerto Vallarta"],"colonias":["Santa Cruz de Quelitán (Palmillas)"]},"48267":{"estado":"Jalisco","ciudades":["Puerto Vallarta"],"colonias":["Los Llanitos"]},"48276":{"estado":"Jalisco","ciudades":["Puerto Vallarta"],"colonias":["Las Higueras del Hundido","Los Llanitos"]},"48280":{"estado":"Jalisco","ciudades":["Puerto Vallarta"],"colonias":["24 de Febrero","Banús Vallarta","C.U.C.","Centro de Salud","Colina Universitaria","Costa Dorada","El Paso Real","Getsemaní","Ixtapa","Ixtapa Centro","Jade","Jardines","La Calma","La Colonia","La Esperanza","La Mina","La Mina II","La Vía","Las Flores","Llanitos","Los Cipreses","Los Tamarindos","Niños Héroes","Nuevo Ixtapa","Pacífico Azul","Palmar de Ixtapa","Palmares Universidad","Paraíso","Paseos Universidad","Paseos Universidad II","Primero de Mayo","Real Ixtapa","San Francisco","Santo Domingo","Verde Vallarta","Villas Ixtapa","Vista Hermosa"]},"48283":{"estado":"Jalisco","ciudades":["Puerto Vallarta"],"colonias":["El Ranchito (El Colesio)","La Desembocada"]},"48284":{"estado":"Jalisco","ciudades":["Puerto Vallarta"],"colonias":["Colinas del Valle","Ecoterra","El Cantón","Joyas del Colorado","La Arboleda (Lomas del Valle)","Los Ángeles","Ojo de Agua","Rancho Nácar"]},"48290":{"estado":"Jalisco","ciudades":["Puerto Vallarta"],"colonias":["12 de Octubre","9 de Octubre","Ampliación Vista Dorada","Ampliación Vista Hermosa","Balcones Vallarta","Bosque del Progreso","Brisas del Pacifico","Campestre Las Cañadas","Campestre San Nicolás","Campo Verde","Club de Golf Vista Vallarta","Coapinole","Colinas de la Bahía","Copa del Rey","Del Villar","El Calvario","El Conejo","El Mangal","El Palmar del Progreso","El Salitrillo","Garza Blanca","Héroes de La Patria","Hipódromo","Joyas del Pedregal","La Floresta","La Primavera","La Trinidad","Laguna del Valle","Las Mojoneras","Leandro Valle","Lisboa","Loma Bonita","Lomas de Coapinole","Lomas de Enmedio","Lomas de San Nicolás","Lomas Del Calvario","Lomas del Progreso","Los Médanos","Magisterio","Magnolias Residencial","Maralta","Maravillas Vallarta","Morelos y Pavón","Palma Real","Parques Universidad (Sendero de Luna)","Paseos de La Ribera","Pitillal Centro","Prados de la Montaña","Progreso","Rancho Alegre","San Esteban","San Miguel","San Nicolás","Sendero del Parque","Sendero las Galeanas","Valle del Mar","Valle Dorado","Villa de Guadalupe","Villas del Prado","Villas del Real","Villas Universidad","Vista al Mar","Vista Dorada","Vista Hermosa II","Volcanes"]},"48291":{"estado":"Jalisco","ciudades":["Puerto Vallarta"],"colonias":["Andalucía","De las Juntas Delegación","Ébano","El Crucero","Loma Bonita","San José","Villa Paradiso","Villas las Juntas","Villas Las Palmas","Zyan"]},"48292":{"estado":"Jalisco","ciudades":["Puerto Vallarta"],"colonias":["Boca de Tomatlán"]},"48294":{"estado":"Jalisco","ciudades":["Puerto Vallarta"],"colonias":["Mismaloya","Sierra del Mar"]},"48296":{"estado":"Jalisco","ciudades":["Puerto Vallarta"],"colonias":["Del Toro","La Playita"]},"48298":{"estado":"Jalisco","ciudades":["Puerto Vallarta"],"colonias":["Bobadilla"]},"48300":{"estado":"Jalisco","ciudades":["Puerto Vallarta"],"colonias":["Puerto Vallarta Centro"]},"48304":{"estado":"Jalisco","ciudades":["Puerto Vallarta"],"colonias":["El Cerro"]},"48310":{"estado":"Jalisco","ciudades":["Puerto Vallarta"],"colonias":["Díaz Ordaz","Los Mangos","Versalles"]},"48312":{"estado":"Jalisco","ciudades":["Puerto Vallarta"],"colonias":["Residencial Fluvial Vallarta"]},"48313":{"estado":"Jalisco","ciudades":["Puerto Vallarta"],"colonias":["FOVISSSTE 100","Jardines de La Higuera","Prados de la Higuera","Primavera de Vallarta","Vallarta Villas","Villas Rio"]},"48314":{"estado":"Jalisco","ciudades":["Puerto Vallarta"],"colonias":["Aramara","El Palmar de Aramara","La Joya","La Marina","Montesori","Puerta del Sol Residencial","Tabachines","Vallarta 750"]},"48315":{"estado":"Jalisco","ciudades":["Puerto Vallarta"],"colonias":["Agua Zarca","Albatros","Arboledas","Jardines Del Puerto","Las Moras","Los Portales","Vallarta 500","Villas del Mar","Villas Del Puerto","Villas Sol"]},"48317":{"estado":"Jalisco","ciudades":["Puerto Vallarta"],"colonias":["Aeropuerto","Guadalupe Victoria","Parques las Palmas","Rincón del Puerto"]},"48318":{"estado":"Jalisco","ciudades":["Puerto Vallarta"],"colonias":["Haciendas Del Pitilla","INFONAVIT CTM","Vida Vallarta"]},"48320":{"estado":"Jalisco","ciudades":["Puerto Vallarta"],"colonias":["La Vena","Mariano Otero","Valentín Gómez Farias"]},"48325":{"estado":"Jalisco","ciudades":["Puerto Vallarta"],"colonias":["Delfines","Ignacio L Vallarta","Niños Héroes","Primavera","Primero de Mayo","Santa Maria"]},"48327":{"estado":"Jalisco","ciudades":["Puerto Vallarta"],"colonias":["Cristóbal Colon","Independencia","Playa Grande (San Pedro)"]},"48328":{"estado":"Jalisco","ciudades":["Puerto Vallarta"],"colonias":["Fovissste 96","Gaviotas","Jardines de Vallarta","Las Aralias","Los Sauces"]},"48330":{"estado":"Jalisco","ciudades":["Puerto Vallarta"],"colonias":["Lázaro Cárdenas","Olímpica"]},"48333":{"estado":"Jalisco","ciudades":["Puerto Vallarta"],"colonias":["Las Glorias","Los Tules","Terminal Marítima","Zona Hotelera Norte","Zona Hotelera Sur"]},"48334":{"estado":"Jalisco","ciudades":["Puerto Vallarta"],"colonias":["Marina Sol","Puerto Iguanas"]},"48335":{"estado":"Jalisco","ciudades":["Puerto Vallarta"],"colonias":["Bocanegra","Marina Vallarta","Villa las Flores"]},"48338":{"estado":"Jalisco","ciudades":["Puerto Vallarta"],"colonias":["Educación","El Carmen","La Aurora","Villas Primavera"]},"48339":{"estado":"Jalisco","ciudades":["Puerto Vallarta"],"colonias":["Puerto Vallarta (Licenciado Gustavo Díaz Ordaz)"]},"48340":{"estado":"Jalisco","ciudades":["Puerto Vallarta"],"colonias":["Agua Azul","Bugambilias","Herradura","López Mateos"]},"48343":{"estado":"Jalisco","ciudades":["Puerto Vallarta"],"colonias":["Campestre las Palmas","La Pedrera","Lomas Del Pedregal","Ramblases"]},"48344":{"estado":"Jalisco","ciudades":["Puerto Vallarta"],"colonias":["Del Mar","Jardines","La Moderna","Linda Vista Océano","Ojo de Agua","Presidentes Municipales","Santa Maria"]},"48350":{"estado":"Jalisco","ciudades":["Puerto Vallarta"],"colonias":["5 de Diciembre"]},"48353":{"estado":"Jalisco","ciudades":["Puerto Vallarta"],"colonias":["Gastronómicos"]},"48360":{"estado":"Jalisco","ciudades":["Puerto Vallarta"],"colonias":["El Caloso","Las Canoas","Las Peñas"]},"48370":{"estado":"Jalisco","ciudades":["Puerto Vallarta"],"colonias":["Buenos Aires"]},"48373":{"estado":"Jalisco","ciudades":["Puerto Vallarta"],"colonias":["Los Robles","Paso Ancho","Paso del Guayabo","Paso Del Molino"]},"48380":{"estado":"Jalisco","ciudades":["Puerto Vallarta"],"colonias":["Altavista","Emiliano Zapata"]},"48389":{"estado":"Jalisco","ciudades":["Puerto Vallarta"],"colonias":["Benito Juárez","El Remance"]},"48399":{"estado":"Jalisco","ciudades":["Puerto Vallarta"],"colonias":["Amapas","Conchas Chinas","El Nogalito"]},"48400":{"estado":"Jalisco","ciudades":["Cabo Corrientes"],"colonias":["El Tuito","La Hermita","Llano de los Laureles"]},"48410":{"estado":"Jalisco","ciudades":["Cabo Corrientes"],"colonias":["La Sauceda"]},"48413":{"estado":"Jalisco","ciudades":["Cabo Corrientes"],"colonias":["Zicatán"]},"48414":{"estado":"Jalisco","ciudades":["Cabo Corrientes"],"colonias":["Los Corrales"]},"48415":{"estado":"Jalisco","ciudades":["Cabo Corrientes"],"colonias":["Chimo"]},"48416":{"estado":"Jalisco","ciudades":["Cabo Corrientes"],"colonias":["Llano Grande de Ipala"]},"48417":{"estado":"Jalisco","ciudades":["Cabo Corrientes"],"colonias":["Aquiles Serdán","Maito","Naranjitos (Arroyo Seco)","Tehuamixtle (Tehualmixtle)"]},"48419":{"estado":"Jalisco","ciudades":["Cabo Corrientes"],"colonias":["Ipala","Peregrina de Gómez (La Boquita)","Villa del Mar"]},"48420":{"estado":"Jalisco","ciudades":["Cabo Corrientes"],"colonias":["El Refugio Suchitlán (La Congregación)"]},"48422":{"estado":"Jalisco","ciudades":["Cabo Corrientes"],"colonias":["Yelapa"]},"48423":{"estado":"Jalisco","ciudades":["Cabo Corrientes"],"colonias":["Ixtlahuahuey"]},"48424":{"estado":"Jalisco","ciudades":["Cabo Corrientes"],"colonias":["Quimixto"]},"48425":{"estado":"Jalisco","ciudades":["Cabo Corrientes"],"colonias":["Las Juntas y los Veranos"]},"48426":{"estado":"Jalisco","ciudades":["Cabo Corrientes"],"colonias":["El Columpio","La Ciénega","Pedro Moreno"]},"48427":{"estado":"Jalisco","ciudades":["Cabo Corrientes"],"colonias":["Chacala"]},"48428":{"estado":"Jalisco","ciudades":["Cabo Corrientes"],"colonias":["Las Guásimas"]},"48430":{"estado":"Jalisco","ciudades":["Cabo Corrientes"],"colonias":["Paulo"]},"48432":{"estado":"Jalisco","ciudades":["Cabo Corrientes"],"colonias":["Los Plátanos","Potrerillos del Tuito"]},"48433":{"estado":"Jalisco","ciudades":["Cabo Corrientes"],"colonias":["Bioto"]},"48445":{"estado":"Jalisco","ciudades":["Cabo Corrientes"],"colonias":["Provincia (Los Húmedos)"]},"48447":{"estado":"Jalisco","ciudades":["Cabo Corrientes"],"colonias":["El Rincón de los Olotes (El Rincón)","Las Juntas del Tuito (Puente la Puchiteca)"]},"48448":{"estado":"Jalisco","ciudades":["Cabo Corrientes"],"colonias":["Santa Cruz del Tuito"]},"48450":{"estado":"Jalisco","ciudades":["Tomatlán"],"colonias":["Azteca","Centro Tomatlán","Gargantillo (La Hacienda)","Indígena","Las Primaveras","Nuevo Santiago","Presa Cajón de Peña (La Presa)","Tierritas Blancas"]},"48451":{"estado":"Jalisco","ciudades":["Tomatlán"],"colonias":["Las Partidas"]},"48453":{"estado":"Jalisco","ciudades":["Tomatlán"],"colonias":["El Corrido","La Piedra Pintada"]},"48454":{"estado":"Jalisco","ciudades":["Tomatlán"],"colonias":["La Villita"]},"48455":{"estado":"Jalisco","ciudades":["Tomatlán"],"colonias":["La Gloria","Plan de Ayala","Vicente Guerrero (Las Lomas Coloradas)"]},"48456":{"estado":"Jalisco","ciudades":["Tomatlán"],"colonias":["Campamento SAGAR Las Palmas","El Crucero","El Naranjo","José María Pino Suárez (Nuevo Nahuapa)","Nahuapa"]},"48457":{"estado":"Jalisco","ciudades":["Tomatlán"],"colonias":["Las Lomas (Las Lomas de Malobaco)","Teocinte (Teocintle)"]},"48458":{"estado":"Jalisco","ciudades":["Tomatlán"],"colonias":["El Tigre"]},"48460":{"estado":"Jalisco","ciudades":["Tomatlán"],"colonias":["La Cruz de Loreto"]},"48461":{"estado":"Jalisco","ciudades":["Tomatlán"],"colonias":["Piloto (Corralito de Piloto)"]},"48462":{"estado":"Jalisco","ciudades":["Tomatlán"],"colonias":["El Realito"]},"48464":{"estado":"Jalisco","ciudades":["Tomatlán"],"colonias":["Crucero del Aval","El Mapache","Pochotitán"]},"48465":{"estado":"Jalisco","ciudades":["Tomatlán"],"colonias":["Benito Juárez (Adolfo Ruiz Cortines)","El Tule"]},"48466":{"estado":"Jalisco","ciudades":["Tomatlán"],"colonias":["Tequesquite"]},"48470":{"estado":"Jalisco","ciudades":["Tomatlán"],"colonias":["San Rafael de los Moreno"]},"48473":{"estado":"Jalisco","ciudades":["Tomatlán"],"colonias":["Cimarronas","El Ocotillo"]},"48475":{"estado":"Jalisco","ciudades":["Tomatlán"],"colonias":["Llano Grande","Santa Gertrudis"]},"48479":{"estado":"Jalisco","ciudades":["Tomatlán"],"colonias":["Cabrel"]},"48480":{"estado":"Jalisco","ciudades":["Tomatlán"],"colonias":["Campo Acosta"]},"48481":{"estado":"Jalisco","ciudades":["Tomatlán"],"colonias":["La Cumbre","La Pintada","Valle de Majahuas (El Poblado)"]},"48485":{"estado":"Jalisco","ciudades":["Tomatlán"],"colonias":["Emiliano Zapata Yautepec (Agua Zarca)","Lázaro Cárdenas (La Nancy)"]},"48486":{"estado":"Jalisco","ciudades":["Tomatlán"],"colonias":["El Aserradero"]},"48490":{"estado":"Jalisco","ciudades":["Tomatlán"],"colonias":["Higuera Blanca"]},"48491":{"estado":"Jalisco","ciudades":["Tomatlán"],"colonias":["Palmillas"]},"48495":{"estado":"Jalisco","ciudades":["Tomatlán"],"colonias":["José María Morelos"]},"48496":{"estado":"Jalisco","ciudades":["Tomatlán"],"colonias":["Puentecillas"]},"48499":{"estado":"Jalisco","ciudades":["Tomatlán"],"colonias":["El Limón","Llano del Toro"]},"48500":{"estado":"Jalisco","ciudades":["Cocula"],"colonias":["Cocula Centro","De la Cruz","Hacienda La Cruz","La Ascensión","San Juan","San Pedro","Santiago","Villas de la Ascención"]},"48502":{"estado":"Jalisco","ciudades":["Cocula"],"colonias":["La Rinconada"]},"48503":{"estado":"Jalisco","ciudades":["Cocula"],"colonias":["Lomas de Cocula","Villa de Casares"]},"48504":{"estado":"Jalisco","ciudades":["Cocula"],"colonias":["La Guitarrilla","Lázaro Cárdenas"]},"48506":{"estado":"Jalisco","ciudades":["Cocula"],"colonias":["Santa Teresa"]},"48507":{"estado":"Jalisco","ciudades":["Cocula"],"colonias":["El Chivatillo (San Isidro)"]},"48508":{"estado":"Jalisco","ciudades":["Cocula"],"colonias":["El Saucillo"]},"48509":{"estado":"Jalisco","ciudades":["Cocula"],"colonias":["Camajapa","Santa Rosa"]},"48510":{"estado":"Jalisco","ciudades":["Cocula"],"colonias":["Agua Caliente","Camichines"]},"48512":{"estado":"Jalisco","ciudades":["Cocula"],"colonias":["San Pablo"]},"48520":{"estado":"Jalisco","ciudades":["Cocula"],"colonias":["La Estanzuela","La Sauceda","San Nicolás"]},"48525":{"estado":"Jalisco","ciudades":["Cocula"],"colonias":["Tateposco (San José Tateposco)"]},"48526":{"estado":"Jalisco","ciudades":["Cocula"],"colonias":["La Puerta del Borrego"]},"48530":{"estado":"Jalisco","ciudades":["Cocula"],"colonias":["La Cofradia de la Luz"]},"48532":{"estado":"Jalisco","ciudades":["Cocula"],"colonias":["Santa Maria"]},"48540":{"estado":"Jalisco","ciudades":["Tecolotlán"],"colonias":["Las Calaveras (Ejido Tenextitlán)","Tecolotlán"]},"48542":{"estado":"Jalisco","ciudades":["Tecolotlán"],"colonias":["Cofradía de Duendes"]},"48546":{"estado":"Jalisco","ciudades":["Tecolotlán"],"colonias":["Quila"]},"48550":{"estado":"Jalisco","ciudades":["Tecolotlán"],"colonias":["Palo Alto"]},"48553":{"estado":"Jalisco","ciudades":["Tecolotlán"],"colonias":["El Rodeo Viejo (El Copal Colorado)"]},"48554":{"estado":"Jalisco","ciudades":["Tecolotlán"],"colonias":["Ojo de Agua"]},"48555":{"estado":"Jalisco","ciudades":["Tecolotlán"],"colonias":["Villegas"]},"48556":{"estado":"Jalisco","ciudades":["Tecolotlán"],"colonias":["Los Ailes","Los Cuartos"]},"48558":{"estado":"Jalisco","ciudades":["Tecolotlán"],"colonias":["Ambrosio"]},"48559":{"estado":"Jalisco","ciudades":["Tecolotlán"],"colonias":["Quililla"]},"48560":{"estado":"Jalisco","ciudades":["Tecolotlán"],"colonias":["Ayotitlán"]},"48563":{"estado":"Jalisco","ciudades":["Tecolotlán"],"colonias":["Caleras Cruz de Mayo (Calfinas)","Tamazulita"]},"48564":{"estado":"Jalisco","ciudades":["Tecolotlán"],"colonias":["San Rafael"]},"48568":{"estado":"Jalisco","ciudades":["Tecolotlán"],"colonias":["San José"]},"48569":{"estado":"Jalisco","ciudades":["Tecolotlán"],"colonias":["San Buenaventura"]},"48570":{"estado":"Jalisco","ciudades":["Tenamaxtlán"],"colonias":["El Ranchito","La Ladera","Tenamaxtlan"]},"48575":{"estado":"Jalisco","ciudades":["Tenamaxtlán"],"colonias":["La Florida"]},"48577":{"estado":"Jalisco","ciudades":["Tenamaxtlán"],"colonias":["Juanacatlan"]},"48580":{"estado":"Jalisco","ciudades":["Tenamaxtlán"],"colonias":["Miraplanes"]},"48585":{"estado":"Jalisco","ciudades":["Tenamaxtlán"],"colonias":["Los Encinos"]},"48590":{"estado":"Jalisco","ciudades":["Tenamaxtlán"],"colonias":["Palo Blanco"]},"48592":{"estado":"Jalisco","ciudades":["Tenamaxtlán"],"colonias":["Colotitlán","El Salatillo"]},"48595":{"estado":"Jalisco","ciudades":["Tenamaxtlán"],"colonias":["San Ignacio"]},"48600":{"estado":"Jalisco","ciudades":["Juchitlán"],"colonias":["Juchitlán","Los Corrales (Villa de Guadalupe)"]},"48605":{"estado":"Jalisco","ciudades":["Juchitlán"],"colonias":["Cofradía de Abajo"]},"48610":{"estado":"Jalisco","ciudades":["Juchitlán"],"colonias":["Santa Maria"]},"48614":{"estado":"Jalisco","ciudades":["Juchitlán"],"colonias":["Los Ojos de Agua"]},"48615":{"estado":"Jalisco","ciudades":["Juchitlán"],"colonias":["Camichines"]},"48620":{"estado":"Jalisco","ciudades":["Juchitlán"],"colonias":["La Tinaja"]},"48625":{"estado":"Jalisco","ciudades":["Juchitlán"],"colonias":["Las Juntas"]},"48626":{"estado":"Jalisco","ciudades":["Juchitlán"],"colonias":["La Candelaria"]},"48628":{"estado":"Jalisco","ciudades":["Juchitlán"],"colonias":["Rancho Viejo"]},"48630":{"estado":"Jalisco","ciudades":["Juchitlán"],"colonias":["Los Guajes"]},"48634":{"estado":"Jalisco","ciudades":["Juchitlán"],"colonias":["Agua Escondida"]},"48635":{"estado":"Jalisco","ciudades":["Juchitlán"],"colonias":["El Aguacate de Arriba"]},"48640":{"estado":"Jalisco","ciudades":["Chiquilistlán"],"colonias":["Chiquilistlan"]},"48644":{"estado":"Jalisco","ciudades":["Chiquilistlán"],"colonias":["Cítala"]},"48650":{"estado":"Jalisco","ciudades":["Chiquilistlán"],"colonias":["Jalpa"]},"48654":{"estado":"Jalisco","ciudades":["Chiquilistlán"],"colonias":["La Cofradia de Jalpa"]},"48655":{"estado":"Jalisco","ciudades":["Chiquilistlán"],"colonias":["Comala y Agua Puerca"]},"48670":{"estado":"Jalisco","ciudades":["Ejutla"],"colonias":["La Labor"]},"48679":{"estado":"Jalisco","ciudades":["Ejutla"],"colonias":["San Lorenzo"]},"48680":{"estado":"Jalisco","ciudades":["Ejutla"],"colonias":["Ejutla","La Cruz"]},"48685":{"estado":"Jalisco","ciudades":["Ejutla"],"colonias":["Amacuautitlanejo"]},"48686":{"estado":"Jalisco","ciudades":["Ejutla"],"colonias":["El Estanco"]},"48687":{"estado":"Jalisco","ciudades":["Ejutla"],"colonias":["Cuyotomate","Los Naranjos de Abajo","Mesa de San Nicolás"]},"48700":{"estado":"Jalisco","ciudades":["El Limón"],"colonias":["El Limón"]},"48708":{"estado":"Jalisco","ciudades":["El Limón"],"colonias":["El Palmar de San Antonio"]},"48710":{"estado":"Jalisco","ciudades":["El Limón"],"colonias":["San Roque"]},"48715":{"estado":"Jalisco","ciudades":["El Limón"],"colonias":["San Miguel Hidalgo"]},"48720":{"estado":"Jalisco","ciudades":["El Limón"],"colonias":["La Ciénega"]},"48725":{"estado":"Jalisco","ciudades":["El Limón"],"colonias":["San Juan de Amula"]},"48730":{"estado":"Jalisco","ciudades":["El Limón"],"colonias":["San Buenaventura"]},"48739":{"estado":"Jalisco","ciudades":["El Limón"],"colonias":["El Rodeo"]},"48740":{"estado":"Jalisco","ciudades":["El Grullo"],"colonias":["El Grullo Centro","San Pedro"]},"48742":{"estado":"Jalisco","ciudades":["El Grullo"],"colonias":["Charco de los Adobes","El Cerrito","El Pedregal","Mirador del Rosal","Pocito Santo","Senderos del Manantial"]},"48743":{"estado":"Jalisco","ciudades":["El Grullo"],"colonias":["Del Sur","Jardines de Manantlán","La Quinta","Las Flores","Oriente 1ra. Sección","Oriente 2da. Sección","Teposilama"]},"48744":{"estado":"Jalisco","ciudades":["El Grullo"],"colonias":["10 de Mayo","7 de Abril","Colomitos","Colomos","Del Álamo","El Álamo","Ixtlán","Juan Canal","Juaquiniquil","La Noria","Laureles","Lomas del Valle","Palma Sola","Patria","Residencial","San Pedro","Santa Cecilia"]},"48745":{"estado":"Jalisco","ciudades":["El Grullo"],"colonias":["Ayuquila","El Cacalote","La Laja"]},"48747":{"estado":"Jalisco","ciudades":["El Grullo"],"colonias":["La Puerta del Barro"]},"48748":{"estado":"Jalisco","ciudades":["El Grullo"],"colonias":["Las Pilas"]},"48750":{"estado":"Jalisco","ciudades":["El Grullo"],"colonias":["Palo Blanco"]},"48753":{"estado":"Jalisco","ciudades":["El Grullo"],"colonias":["El Aguacate"]},"48760":{"estado":"Jalisco","ciudades":["Tonaya"],"colonias":["Guadalupana","La Aviación","La Cofradía","San Luis Tenango","Tonaya"]},"48763":{"estado":"Jalisco","ciudades":["Tonaya"],"colonias":["Las Liebres","Los González"]},"48764":{"estado":"Jalisco","ciudades":["Tonaya"],"colonias":["Amacuautitlán"]},"48765":{"estado":"Jalisco","ciudades":["Tonaya"],"colonias":["Coatlancillo"]},"48766":{"estado":"Jalisco","ciudades":["Tonaya"],"colonias":["El Paso de San Francisco","Las Higueras"]},"48767":{"estado":"Jalisco","ciudades":["Tonaya"],"colonias":["El Cerrito","Tecomatlán"]},"48768":{"estado":"Jalisco","ciudades":["Tonaya"],"colonias":["Los Asmoles","San Rafael"]},"48769":{"estado":"Jalisco","ciudades":["Tonaya"],"colonias":["Atarjeas de Covarrubias (San Isidro)"]},"48770":{"estado":"Jalisco","ciudades":["Tuxcacuesco"],"colonias":["Tuxcacuesco"]},"48775":{"estado":"Jalisco","ciudades":["Tuxcacuesco"],"colonias":["Chachahuatlan"]},"48777":{"estado":"Jalisco","ciudades":["Tuxcacuesco"],"colonias":["El Camichín"]},"48778":{"estado":"Jalisco","ciudades":["Tuxcacuesco"],"colonias":["La Cañita","Ventanas","Zenzontla"]},"48780":{"estado":"Jalisco","ciudades":["Tuxcacuesco"],"colonias":["Los González"]},"48785":{"estado":"Jalisco","ciudades":["Tuxcacuesco"],"colonias":["El Platanar"]},"48786":{"estado":"Jalisco","ciudades":["Tuxcacuesco"],"colonias":["San Miguel"]},"48788":{"estado":"Jalisco","ciudades":["Tuxcacuesco"],"colonias":["Apulco"]},"48790":{"estado":"Jalisco","ciudades":["Tuxcacuesco"],"colonias":["El Temascal"]},"48793":{"estado":"Jalisco","ciudades":["Tuxcacuesco"],"colonias":["El Carrizal"]},"48795":{"estado":"Jalisco","ciudades":["Tuxcacuesco"],"colonias":["Palmar de los Camberos"]},"48800":{"estado":"Jalisco","ciudades":["Villa Purificación"],"colonias":["2 de Febrero","La Quinta","Villa Purificación"]},"48802":{"estado":"Jalisco","ciudades":["Villa Purificación"],"colonias":["Benito Juárez","Ejido Purificación","Excuchimilco","Jardines San Roque","Juan Fernández de Hijar","La Morena","Provincia","Reforma"]},"48803":{"estado":"Jalisco","ciudades":["Villa Purificación"],"colonias":["Rancho Dos Hermanos"]},"48804":{"estado":"Jalisco","ciudades":["Villa Purificación"],"colonias":["Arroyo Zarco","El Conejito","El Mangal"]},"48805":{"estado":"Jalisco","ciudades":["Villa Purificación"],"colonias":["Estancia de Amborín"]},"48806":{"estado":"Jalisco","ciudades":["Villa Purificación"],"colonias":["El Pantano (San Francisco los Guajolotes)","Las Vallas"]},"48815":{"estado":"Jalisco","ciudades":["Villa Purificación"],"colonias":["Los Achotes","Paso Real","Rancho Nuevo","San Miguel","Villa Vieja (Ex-Hacienda Villa Vieja)"]},"48816":{"estado":"Jalisco","ciudades":["Villa Purificación"],"colonias":["Casas Altas","El Jengibre","Espinos de Judío"]},"48820":{"estado":"Jalisco","ciudades":["Villa Purificación"],"colonias":["El Chino","Las Guásimas","Los Cimientos","Paso del Tene","Telpitita","Tene","Tepeguaje"]},"48823":{"estado":"Jalisco","ciudades":["Villa Purificación"],"colonias":["El Divisadero","Paso Hondo"]},"48824":{"estado":"Jalisco","ciudades":["Villa Purificación"],"colonias":["Lagunillas","Llano del Oro"]},"48825":{"estado":"Jalisco","ciudades":["Villa Purificación"],"colonias":["Jirosto","La Eca","La Subida Blanca","Los Pozos"]},"48826":{"estado":"Jalisco","ciudades":["Villa Purificación"],"colonias":["El Camalote","El Manguito","Espinos de Carreón"]},"48827":{"estado":"Jalisco","ciudades":["Villa Purificación"],"colonias":["Carreón","El Herradero","Mezcales"]},"48830":{"estado":"Jalisco","ciudades":["Villa Purificación"],"colonias":["Pabelo","Plaza de Gallos"]},"48833":{"estado":"Jalisco","ciudades":["Villa Purificación"],"colonias":["La Atalaya","La Nancita"]},"48835":{"estado":"Jalisco","ciudades":["Villa Purificación"],"colonias":["El Alcíhuatl","La Huerta del Carrizo"]},"48836":{"estado":"Jalisco","ciudades":["Villa Purificación"],"colonias":["El Carrizal","El Limoncito","El Plan de los Plátanos"]},"48837":{"estado":"Jalisco","ciudades":["Villa Purificación"],"colonias":["El Caracol","El Criadero","El Manguito","El Platanar","El Platanillo","Los Aguacates","Rancho Lejos"]},"48840":{"estado":"Jalisco","ciudades":["Villa Purificación"],"colonias":["Juan Diego","Las Guasimitas","Los Ciruelos","Los Lindos","Los Llanitos","Paso del Guamúchil"]},"48843":{"estado":"Jalisco","ciudades":["Villa Purificación"],"colonias":["El Piñal","La Anona","Los Ocotitos"]},"48844":{"estado":"Jalisco","ciudades":["Villa Purificación"],"colonias":["Agua Fría","El Gondo","Tezacuale (Carrizalillo)"]},"48845":{"estado":"Jalisco","ciudades":["Villa Purificación"],"colonias":["Huista","Jocotlán","La Cañada","La Cofradía","Llano del Higo","Rancho Nuevo (Los Tecomates)","Zapotán"]},"48847":{"estado":"Jalisco","ciudades":["Villa Purificación"],"colonias":["Chantecuán","El Carrizal","Las Nancitas"]},"48850":{"estado":"Jalisco","ciudades":["La Huerta"],"colonias":["Cardenista","El Maguey","El Refugio","La Huerta","Plan de Ayala"]},"48860":{"estado":"Jalisco","ciudades":["La Huerta"],"colonias":["Agua Zarquita","Cofradía","El Higueral"]},"48862":{"estado":"Jalisco","ciudades":["La Huerta"],"colonias":["Apamila","Las Pilas","Mazatán"]},"48863":{"estado":"Jalisco","ciudades":["La Huerta"],"colonias":["La Mesa"]},"48865":{"estado":"Jalisco","ciudades":["La Huerta"],"colonias":["Nacastillo"]},"48866":{"estado":"Jalisco","ciudades":["La Huerta"],"colonias":["El Palmar (Adolfo López Mateos)"]},"48867":{"estado":"Jalisco","ciudades":["La Huerta"],"colonias":["Chancoa","Platanitos (La Limonosa)"]},"48868":{"estado":"Jalisco","ciudades":["La Huerta"],"colonias":["El Playón","Quémaro"]},"48869":{"estado":"Jalisco","ciudades":["La Huerta"],"colonias":["Chamela","Juan Gil Preciado","La Fortuna","Los Ranchitos","Pérula","San Mateo","Santa Cruz de Otates"]},"48870":{"estado":"Jalisco","ciudades":["La Huerta"],"colonias":["La Concepción","La Conchita"]},"48872":{"estado":"Jalisco","ciudades":["La Huerta"],"colonias":["Cuatro Vientos","El Totole","Plazola"]},"48873":{"estado":"Jalisco","ciudades":["La Huerta"],"colonias":["Los Árboles"]},"48878":{"estado":"Jalisco","ciudades":["La Huerta"],"colonias":["Francisco Villa"]},"48880":{"estado":"Jalisco","ciudades":["La Huerta"],"colonias":["El Rincón"]},"48883":{"estado":"Jalisco","ciudades":["La Huerta"],"colonias":["Loma Alta"]},"48884":{"estado":"Jalisco","ciudades":["La Huerta"],"colonias":["Comitancito"]},"48889":{"estado":"Jalisco","ciudades":["La Huerta"],"colonias":["Tecuastitan"]},"48890":{"estado":"Jalisco","ciudades":["La Huerta"],"colonias":["Agua Caliente Nueva","Apazulco (Miguel Hidalgo Viejo)","Nuevo Miguel Hidalgo"]},"48892":{"estado":"Jalisco","ciudades":["La Huerta"],"colonias":["Careyes","Cuitzmala","Emiliano Zapata"]},"48893":{"estado":"Jalisco","ciudades":["La Huerta"],"colonias":["Agua Caliente Vieja de Apazulco","El Programa","El Rebalsito de Apazulco","La Rosa"]},"48896":{"estado":"Jalisco","ciudades":["La Huerta"],"colonias":["Arroyo Seco"]},"48898":{"estado":"Jalisco","ciudades":["La Huerta"],"colonias":["La Manzanilla"]},"48900":{"estado":"Jalisco","ciudades":["Autlán de Navarro"],"colonias":["Autlán de Navarro Centro","Guadalupe"]},"48902":{"estado":"Jalisco","ciudades":["Autlán de Navarro"],"colonias":["Azucarera","Bugambilias","Carnaval","Colonos Alameda","Hacienda de Oriente","Hacienda Manantlan","Hacienda Real","Jardín Residencial Autlán","Jardines Autlán","Jardines del Sol","Jardines Universidad","La Calma","La Herradura","La Noria INFONAVIT","Las Américas","Las Parotitas","Lomas de Autlán","Magisterial","Paseos Universidad","Paulino Navarro","Privada Bachilleres","Puerta de la Costa","Residencial Providencia","Rincón Residencial","Rinconada el Cangrejo","Rodríguez Alcaine","Villas de San Francisco","Villas Taurinas"]},"48903":{"estado":"Jalisco","ciudades":["Autlán de Navarro"],"colonias":["Adolfo López Mateos","Camichines","Cerro Colorado","Coajinque","Colinas del Sur","Echeverría","Ejidal","El Paraíso","Las Flores","Las Orquideas","Loma Bonita","Loma del Aire","Loma Dorada","Los Naranjos","Ojuelos las Villas","Presidencial","Puesta del Sol","Suave Patria","Valle de los Leones","Valle del Vergel","Valle la Grana","Villa de San Javier"]},"48904":{"estado":"Jalisco","ciudades":["Autlán de Navarro"],"colonias":["5 de Mayo","Acueducto Capaya","Arboledas","Bancaria","Brisas del Oeste","Cardenista","Castellón","El Cerrito","El Tecolote","Francisco Silva Romero","Huizilacate","IPROVIPE las Ceibas","Jaime Llamas","La Garita","La Grana","La Paloma","La Quebradilla","La Rosa","Las Lanzas","Las Montañas","Lomas de San José","Lomas del Pedregal","Los Arquitos","Obrera","Pintores","Primavera","Privada Valle de las Azucenas","Residencial El Cajete","San José","Santa Rita","Valle Real","Villas de Autlán","Villas de Capaya"]},"48905":{"estado":"Jalisco","ciudades":["Autlán de Navarro"],"colonias":["Chiquihuitlán"]},"48906":{"estado":"Jalisco","ciudades":["Autlán de Navarro"],"colonias":["Ayutita"]},"48907":{"estado":"Jalisco","ciudades":["Autlán de Navarro"],"colonias":["Mezquitán (San Francisco de Abajo)","San Francisco de Arriba"]},"48908":{"estado":"Jalisco","ciudades":["Autlán de Navarro"],"colonias":["El Jalocote","La Lima de los Gómez"]},"48909":{"estado":"Jalisco","ciudades":["Autlán de Navarro"],"colonias":["Agua Hedionda","El Izote"]},"48910":{"estado":"Jalisco","ciudades":["Autlán de Navarro"],"colonias":["Bellavista (El Castillo)","El Rodeo","Lagunillas"]},"48914":{"estado":"Jalisco","ciudades":["Autlán de Navarro"],"colonias":["Chacaltepec","El Corcovado"]},"48915":{"estado":"Jalisco","ciudades":["Autlán de Navarro"],"colonias":["El Chacalito","La Noria"]},"48916":{"estado":"Jalisco","ciudades":["Autlán de Navarro"],"colonias":["La Aldaba","Las Paredes"]},"48917":{"estado":"Jalisco","ciudades":["Autlán de Navarro"],"colonias":["El Mentidero","Volantín"]},"48918":{"estado":"Jalisco","ciudades":["Autlán de Navarro"],"colonias":["El Chante","La Sidrita"]},"48919":{"estado":"Jalisco","ciudades":["Autlán de Navarro"],"colonias":["Rincón de Luisa"]},"48920":{"estado":"Jalisco","ciudades":["Autlán de Navarro"],"colonias":["Ahuacapan"]},"48922":{"estado":"Jalisco","ciudades":["Autlán de Navarro"],"colonias":["Tecomatlan"]},"48923":{"estado":"Jalisco","ciudades":["Autlán de Navarro"],"colonias":["Yerbabuena"]},"48926":{"estado":"Jalisco","ciudades":["Autlán de Navarro"],"colonias":["Tecopatlan"]},"48930":{"estado":"Jalisco","ciudades":["Casimiro Castillo","La Resolana"],"colonias":["Casimiro Castillo Centro","José María Preciado","Las Salias (El Barrito)","Tacubaya"]},"48938":{"estado":"Jalisco","ciudades":["Casimiro Castillo","La Resolana"],"colonias":["Camino Real","Jardín de San Esteban"]},"48939":{"estado":"Jalisco","ciudades":["Casimiro Castillo","La Resolana"],"colonias":["José Ma. Martínez","Juan Gil Preciado"]},"48940":{"estado":"Jalisco","ciudades":["Casimiro Castillo"],"colonias":["El Establo","Lo Arado"]},"48942":{"estado":"Jalisco","ciudades":["Casimiro Castillo"],"colonias":["El Mirador","Nuevo Centro de Población Benito Juárez","Nuevo Centro de Población las Ramas","Nuevo Ejido Corral de Piedra"]},"48943":{"estado":"Jalisco","ciudades":["Casimiro Castillo"],"colonias":["El Zapotillo","Lares Verduzco (Marmolares)","Lindavista"]},"48944":{"estado":"Jalisco","ciudades":["Casimiro Castillo"],"colonias":["La Clavellina","Las Nueces","Puerto los Mazos"]},"48945":{"estado":"Jalisco","ciudades":["Casimiro Castillo"],"colonias":["La Huertita"]},"48946":{"estado":"Jalisco","ciudades":["Casimiro Castillo"],"colonias":["El Bayuelo (Los Contreras)","Los Tecomates","Majoma","Modelo","Piedra Pesada"]},"48947":{"estado":"Jalisco","ciudades":["Casimiro Castillo"],"colonias":["Coyamel (El Coyame)","Las Abejas"]},"48948":{"estado":"Jalisco","ciudades":["Casimiro Castillo"],"colonias":["El Chico","Francisco I. Madero (El Naranjal)"]},"48950":{"estado":"Jalisco","ciudades":["Cuautitlán de García Barragán"],"colonias":["Cuautitlán de García Barragán"]},"48953":{"estado":"Jalisco","ciudades":["Cuautitlán de García Barragán"],"colonias":["Casa Blanca (Revolución Mexicana)"]},"48954":{"estado":"Jalisco","ciudades":["Cuautitlán de García Barragán"],"colonias":["Cuzalapa"]},"48955":{"estado":"Jalisco","ciudades":["Cuautitlán de García Barragán"],"colonias":["El Durazno","La Pareja"]},"48959":{"estado":"Jalisco","ciudades":["Cuautitlán de García Barragán"],"colonias":["Charco Azul","La Nance"]},"48960":{"estado":"Jalisco","ciudades":["Cuautitlán de García Barragán"],"colonias":["Manantlan"]},"48962":{"estado":"Jalisco","ciudades":["Cuautitlán de García Barragán"],"colonias":["Ayotitlán","El Reparo","La Guaca","Ocote Arco (Rincón de Ayotitlán)"]},"48963":{"estado":"Jalisco","ciudades":["Cuautitlán de García Barragán"],"colonias":["La Zorra","Pedregal","Telcruz"]},"48964":{"estado":"Jalisco","ciudades":["Cuautitlán de García Barragán"],"colonias":["Lagunillas de Macoaca"]},"48965":{"estado":"Jalisco","ciudades":["Cuautitlán de García Barragán"],"colonias":["El Refugio (El Tepehuaje)","Los Espinos","Tequesquitlán"]},"48966":{"estado":"Jalisco","ciudades":["Cuautitlán de García Barragán"],"colonias":["Santa Rosa"]},"48967":{"estado":"Jalisco","ciudades":["Cuautitlán de García Barragán"],"colonias":["Chacala","El Chico","Sehuaya"]},"48970":{"estado":"Jalisco","ciudades":["Cihuatlán"],"colonias":["Cihuatlán Centro","El Brasil"]},"48972":{"estado":"Jalisco","ciudades":["Cihuatlán"],"colonias":["Costalegre","Educadores de México","El Barrito","Lomas del Paraíso","Miguel Hidalgo"]},"48973":{"estado":"Jalisco","ciudades":["Cihuatlán"],"colonias":["El Bonete","Peñitas y Truchas"]},"48974":{"estado":"Jalisco","ciudades":["Cihuatlán"],"colonias":["Brisas de Cihuatlán","Casimiro Castillo","Loma Bonita","Miraflores","Miravalle","Nuevo","Santa Cecilia"]},"48980":{"estado":"Jalisco","ciudades":["Cihuatlán"],"colonias":["Cuastecomate","Melaque","San Agustín","San Patricio","Santa Cecilia","Villa Obregón"]},"48983":{"estado":"Jalisco","ciudades":["Cihuatlán"],"colonias":["Emiliano Zapata (El Ranchito)","La Paz"]},"48985":{"estado":"Jalisco","ciudades":["Cihuatlán"],"colonias":["Jaluco","Pinal Villa","San Ignacio de Loyola"]},"48986":{"estado":"Jalisco","ciudades":["Cihuatlán"],"colonias":["El Barrito"]},"48987":{"estado":"Jalisco","ciudades":["Cihuatlán"],"colonias":["Barra de Navidad","Santa Fe"]},"48988":{"estado":"Jalisco","ciudades":["Cihuatlán"],"colonias":["Los Ingenios"]},"48989":{"estado":"Jalisco","ciudades":["Cihuatlán"],"colonias":["Lázaro Cárdenas"]},"48990":{"estado":"Jalisco","ciudades":["Cihuatlán"],"colonias":["Brisas de la Navidad (El Gallo Colorado)","El Aguacate"]},"48995":{"estado":"Jalisco","ciudades":["Cihuatlán"],"colonias":["El Rebalse"]}}